pytest_green_light/__init__.py
pytest_green_light/fixtures.py
pytest_green_light/plugin.py
pytest_green_light-0.2.0.dist-info/LICENSE
pytest_green_light-0.2.0.dist-info/METADATA
pytest_green_light-0.2.0.dist-info/WHEEL
pytest_green_light-0.2.0.dist-info/entry_points.txt
pytest_green_light-0.2.0.dist-info/top_level.txt
pytest_green_light-0.2.0.dist-info/RECORD
