Metadata-Version: 2.1
Name: pytest-green-light
Version: 0.2.0
Summary: Pytest plugin that gives SQLAlchemy async engines the green light - automatically fixes MissingGreenlet errors
Author-email: Odos Matthews <odosmatthews@gmail.com>
Maintainer-email: Odos Matthews <odosmatthews@gmail.com>
License: MIT
Project-URL: Homepage, https://github.com/eddiethedean/pytest-green-light
Project-URL: Documentation, https://github.com/eddiethedean/pytest-green-light#readme
Project-URL: Repository, https://github.com/eddiethedean/pytest-green-light
Project-URL: Issues, https://github.com/eddiethedean/pytest-green-light/issues
Classifier: Development Status :: 3 - Alpha
Classifier: Intended Audience :: Developers
Classifier: License :: OSI Approved :: MIT License
Classifier: Programming Language :: Python :: 3
Classifier: Programming Language :: Python :: 3.8
Classifier: Programming Language :: Python :: 3.9
Classifier: Programming Language :: Python :: 3.10
Classifier: Programming Language :: Python :: 3.11
Classifier: Programming Language :: Python :: 3.12
Classifier: Framework :: Pytest
Requires-Python: >=3.8
License-File: LICENSE
Requires-Dist: pytest>=7.0.0
Requires-Dist: sqlalchemy>=2.0.0
Requires-Dist: greenlet>=2.0.0
Provides-Extra: all
Requires-Dist: pytest-asyncio>=0.21.0; extra == "all"
Requires-Dist: aiosqlite>=0.19.0; extra == "all"
Requires-Dist: asyncpg>=0.28.0; extra == "all"
Requires-Dist: aiomysql>=0.2.0; extra == "all"
Requires-Dist: testing.postgresql>=2.0.0; extra == "all"
Requires-Dist: testing.mysqld>=2.0.0; extra == "all"
Provides-Extra: dev
Requires-Dist: pytest-asyncio>=0.21.0; extra == "dev"
Requires-Dist: aiosqlite>=0.19.0; extra == "dev"
Requires-Dist: black>=23.0.0; extra == "dev"
Requires-Dist: mypy>=1.0.0; extra == "dev"
Requires-Dist: ruff>=0.1.0; extra == "dev"
Requires-Dist: ty>=0.0.1; extra == "dev"
Provides-Extra: mysql
Requires-Dist: aiomysql>=0.2.0; extra == "mysql"
Requires-Dist: testing.mysqld>=2.0.0; extra == "mysql"
Provides-Extra: postgres
Requires-Dist: asyncpg>=0.28.0; extra == "postgres"
Requires-Dist: testing.postgresql>=2.0.0; extra == "postgres"
